coinage/__init__.py
coinage/blockchain.py
coinage/util.py
coinage/validators/__init__.py
coinage/validators/address_validator.py
coinage/validators/base58check.py
coinage/validators/bech32.py
coinage/validators/cashaddr.py
coinage/validators/sha3.py
python_coinage-1.0.0.dist-info/LICENSE
python_coinage-1.0.0.dist-info/METADATA
python_coinage-1.0.0.dist-info/WHEEL
python_coinage-1.0.0.dist-info/top_level.txt
python_coinage-1.0.0.dist-info/RECORD
