Metadata-Version: 2.1
Name: python-coinage
Version: 1.0.0
Summary: Cryptocurrency address validation module
Home-page: https://github.com/FranciscoDA/coinage.git
Author: Francisco Altoe
Author-email: franciscoda@outlook.com
License: UNKNOWN
Platform: UNKNOWN
Requires-Python: >=3.7
Requires-Dist: base58check
Requires-Dist: pysha3
